{
  "runId": "backtest_1763926780902",
  "config": {
    "symbol": "XAUUSD",
    "strategies": [
      "low"
    ],
    "startDate": "2023-10-01",
    "endDate": "2023-10-30",
    "timeframe": "M5",
    "initialBalance": 10000,
    "dataSource": "mt5"
  },
  "startTime": "2025-11-23T19:39:40.902Z",
  "endTime": "2025-11-23T19:40:11.971Z",
  "runtimeMs": 31069,
  "stats": {
    "totalTrades": 20,
    "winningTrades": 4,
    "losingTrades": 16,
    "winRate": 20,
    "totalPnL": -1741.3017000000077,
    "grossProfit": 5624.401799999999,
    "grossLoss": 7365.703500000007,
    "profitFactor": 0.7635932942454164,
    "maxDrawdown": 1778.2373999999927,
    "maxDrawdownPercent": 17.610353077380076,
    "maxConsecutiveLosses": 5,
    "maxConsecutiveWins": 1,
    "averageWin": 1406.1004499999997,
    "averageLoss": 460.35646875000043,
    "averageRr": 1.4000000000000021,
    "expectancy": -87.06508500000041,
    "averageTradeDurationMinutes": 3250.5,
    "perSymbolStats": {
      "XAUUSD": {
        "trades": 20,
        "pnl": -1741.3017000000077,
        "winRate": 20
      }
    },
    "perStrategyStats": {
      "low": {
        "trades": 20,
        "pnl": -1741.3017000000077,
        "winRate": 20
      }
    },
    "smcStats": {
      "htf": {
        "totalSwings": 715,
        "swingHighs": 386,
        "swingLows": 329,
        "averageSwingsPerEvaluation": 1.1837748344370862,
        "totalBOS": 775,
        "bullishBOS": 534,
        "bearishBOS": 241,
        "totalCHoCH": 0,
        "bullishCHoCH": 0,
        "bearishCHoCH": 0,
        "totalMSB": 0,
        "bullishMSB": 0,
        "bearishMSB": 0,
        "trendBullish": 53,
        "trendBearish": 23,
        "trendSideways": 528,
        "evaluations": 604
      },
      "itf": {
        "totalSwings": 1383,
        "swingHighs": 707,
        "swingLows": 676,
        "averageSwingsPerEvaluation": 2.2746710526315788,
        "totalBOS": 2145,
        "bullishBOS": 1177,
        "bearishBOS": 968,
        "totalCHoCH": 10,
        "bullishCHoCH": 5,
        "bearishCHoCH": 5,
        "totalMSB": 0,
        "bullishMSB": 0,
        "bearishMSB": 0,
        "trendBullish": 0,
        "trendBearish": 0,
        "trendSideways": 608,
        "evaluations": 608
      },
      "ltf": {
        "totalSwings": 943,
        "swingHighs": 492,
        "swingLows": 451,
        "averageSwingsPerEvaluation": 1.550986842105263,
        "totalBOS": 793,
        "bullishBOS": 439,
        "bearishBOS": 354,
        "totalCHoCH": 2,
        "bullishCHoCH": 0,
        "bearishCHoCH": 2,
        "totalMSB": 0,
        "bullishMSB": 0,
        "bearishMSB": 0,
        "trendBullish": 33,
        "trendBearish": 33,
        "trendSideways": 542,
        "evaluations": 608
      },
      "totalEvaluations": 608
    }
  },
  "initialBalance": 10000,
  "finalBalance": 8258.698299999993,
  "totalReturn": -1741.3017000000073,
  "totalReturnPercent": -17.41301700000007
}