{
  "runId": "backtest_1764027413969",
  "config": {
    "symbol": "XAUUSD",
    "strategies": [
      "low"
    ],
    "startDate": "2024-05-01",
    "endDate": "2024-05-07",
    "timeframe": "M5",
    "initialBalance": 10000,
    "dataSource": "mt5"
  },
  "startTime": "2025-11-24T23:36:53.969Z",
  "endTime": "2025-11-24T23:37:08.677Z",
  "runtimeMs": 14708,
  "stats": {
    "totalTrades": 0,
    "winningTrades": 0,
    "losingTrades": 0,
    "breakEvenTrades": 0,
    "winRate": 0,
    "totalPnL": 0,
    "grossProfit": 0,
    "grossLoss": 0,
    "profitFactor": 0,
    "maxDrawdown": 0,
    "maxDrawdownPercent": 0,
    "maxConsecutiveLosses": 0,
    "maxConsecutiveWins": 0,
    "averageWin": 0,
    "averageLoss": 0,
    "averageRr": 0,
    "expectancy": 0,
    "averageTradeDurationMinutes": 0,
    "perSymbolStats": {},
    "perStrategyStats": {},
    "smcStats": {
      "htf": {
        "totalSwings": 3014,
        "swingHighs": 1487,
        "swingLows": 1527,
        "averageSwingsPerEvaluation": 4.380813953488372,
        "totalBOS": 9791,
        "bullishBOS": 4871,
        "bearishBOS": 4920,
        "totalCHoCH": 110,
        "bullishCHoCH": 22,
        "bearishCHoCH": 88,
        "totalMSB": 1,
        "bullishMSB": 0,
        "bearishMSB": 1,
        "trendBullish": 137,
        "trendBearish": 123,
        "trendSideways": 428,
        "evaluations": 688
      },
      "itf": {
        "totalSwings": 1798,
        "swingHighs": 899,
        "swingLows": 899,
        "averageSwingsPerEvaluation": 2.613372093023256,
        "totalBOS": 2788,
        "bullishBOS": 1451,
        "bearishBOS": 1337,
        "totalCHoCH": 19,
        "bullishCHoCH": 11,
        "bearishCHoCH": 8,
        "totalMSB": 0,
        "bullishMSB": 0,
        "bearishMSB": 0,
        "trendBullish": 0,
        "trendBearish": 0,
        "trendSideways": 688,
        "evaluations": 688
      },
      "ltf": {
        "totalSwings": 1170,
        "swingHighs": 569,
        "swingLows": 601,
        "averageSwingsPerEvaluation": 1.6981132075471699,
        "totalBOS": 1245,
        "bullishBOS": 606,
        "bearishBOS": 639,
        "totalCHoCH": 3,
        "bullishCHoCH": 0,
        "bearishCHoCH": 3,
        "totalMSB": 0,
        "bullishMSB": 0,
        "bearishMSB": 0,
        "trendBullish": 53,
        "trendBearish": 46,
        "trendSideways": 590,
        "evaluations": 689
      },
      "totalEvaluations": 689
    }
  },
  "initialBalance": 10000,
  "finalBalance": 10000,
  "totalReturn": 0,
  "totalReturnPercent": 0
}