{
  "months": [
    {
      "month": "2023-01",
      "startDate": "2023-01-01",
      "endDate": "2023-01-31",
      "trades": 55,
      "winRate": 16.363636363636363,
      "totalPnL": -5932.5425893233105,
      "profitFactor": 0.5860197861055068,
      "avgRR": 1.327272727272727,
      "maxDrawdown": 6136.719448537064,
      "maxDrawdownPercent": 61.36719448537063,
      "totalReturn": -5932.542589323311,
      "totalReturnPercent": -59.32542589323312,
      "expectancy": -107.86441071496938,
      "runtimeMs": 63502,
      "success": true
    },
    {
      "month": "2023-02",
      "startDate": "2023-02-01",
      "endDate": "2023-02-28",
      "trades": 39,
      "winRate": 20.51282051282051,
      "totalPnL": -2850.2069771514202,
      "profitFactor": 0.7783493689081407,
      "avgRR": 1.41025641025641,
      "maxDrawdown": 3349.933576024284,
      "maxDrawdownPercent": 33.499335760242836,
      "totalReturn": -2850.206977151418,
      "totalReturnPercent": -28.502069771514176,
      "expectancy": -73.08223018336986,
      "runtimeMs": 44866,
      "success": true
    },
    {
      "month": "2023-03",
      "startDate": "2023-03-01",
      "endDate": "2023-03-31",
      "trades": 34,
      "winRate": 23.52941176470588,
      "totalPnL": -963.5954067500575,
      "profitFactor": 0.9224239143527908,
      "avgRR": 1.4705882352941182,
      "maxDrawdown": 2926.7405684212245,
      "maxDrawdownPercent": 27.19306657522413,
      "totalReturn": -963.5954067500588,
      "totalReturnPercent": -9.635954067500588,
      "expectancy": -28.34104137500185,
      "runtimeMs": 51674,
      "success": true
    },
    {
      "month": "2023-04",
      "startDate": "2023-04-01",
      "endDate": "2023-04-30",
      "trades": 41,
      "winRate": 21.951219512195124,
      "totalPnL": -2467.366737741372,
      "profitFactor": 0.8217899228363713,
      "avgRR": 1.4390243902439028,
      "maxDrawdown": 3508.295144909199,
      "maxDrawdownPercent": 34.087660250106524,
      "totalReturn": -2467.366737741373,
      "totalReturnPercent": -24.67366737741373,
      "expectancy": -60.17967653027739,
      "runtimeMs": 47457,
      "success": true
    },
    {
      "month": "2023-05",
      "startDate": "2023-05-01",
      "endDate": "2023-05-31",
      "trades": 36,
      "winRate": 25,
      "totalPnL": -326.75438982231617,
      "profitFactor": 0.9784182452633599,
      "avgRR": 1.500000000000002,
      "maxDrawdown": 3998.6436564650685,
      "maxDrawdownPercent": 29.08018464533411,
      "totalReturn": -326.7543898223121,
      "totalReturnPercent": -3.2675438982231206,
      "expectancy": -9.076510828397602,
      "runtimeMs": 48906,
      "success": true
    },
    {
      "month": "2023-06",
      "startDate": "2023-06-01",
      "endDate": "2023-06-30",
      "trades": 41,
      "winRate": 26.82926829268293,
      "totalPnL": 1028.1886338186382,
      "profitFactor": 1.0677410717790232,
      "avgRR": 1.5365853658536592,
      "maxDrawdown": 2258.50224802487,
      "maxDrawdownPercent": 21.431468323292936,
      "totalReturn": 1028.1886338186432,
      "totalReturnPercent": 10.281886338186432,
      "expectancy": 25.077771556552136,
      "runtimeMs": 44605,
      "success": true
    },
    {
      "month": "2023-07",
      "startDate": "2023-07-01",
      "endDate": "2023-07-31",
      "trades": 41,
      "winRate": 26.82926829268293,
      "totalPnL": 927.5524751707774,
      "profitFactor": 1.0532065302477283,
      "avgRR": 1.5365853658536592,
      "maxDrawdown": 4256.681894719453,
      "maxDrawdownPercent": 30.849086349446598,
      "totalReturn": 927.552475170778,
      "totalReturnPercent": 9.275524751707781,
      "expectancy": 22.623231101726333,
      "runtimeMs": 51712,
      "success": true
    },
    {
      "month": "2023-08",
      "startDate": "2023-08-01",
      "endDate": "2023-08-31",
      "trades": 43,
      "winRate": 18.6046511627907,
      "totalPnL": -4386.082142379776,
      "profitFactor": 0.6750342210514773,
      "avgRR": 1.3720930232558148,
      "maxDrawdown": 4406.581238954442,
      "maxDrawdownPercent": 43.94281577928009,
      "totalReturn": -4386.082142379775,
      "totalReturnPercent": -43.86082142379775,
      "expectancy": -102.00191028790175,
      "runtimeMs": 57763,
      "success": true
    },
    {
      "month": "2023-09",
      "startDate": "2023-09-01",
      "endDate": "2023-09-30",
      "trades": 40,
      "winRate": 15,
      "totalPnL": -5926.9596094325825,
      "profitFactor": 0.44237105961701784,
      "avgRR": 1.3,
      "maxDrawdown": 5926.959609432584,
      "maxDrawdownPercent": 59.26959609432584,
      "totalReturn": -5926.959609432584,
      "totalReturnPercent": -59.26959609432584,
      "expectancy": -148.17399023581467,
      "runtimeMs": 50113,
      "success": true
    },
    {
      "month": "2023-10",
      "startDate": "2023-10-01",
      "endDate": "2023-10-31",
      "trades": 44,
      "winRate": 22.727272727272727,
      "totalPnL": -2355.328043897559,
      "profitFactor": 0.8431774094466477,
      "avgRR": 1.4545454545454548,
      "maxDrawdown": 3164.632464434043,
      "maxDrawdownPercent": 30.89183743007139,
      "totalReturn": -2355.3280438975544,
      "totalReturnPercent": -23.553280438975545,
      "expectancy": -53.53018281585372,
      "runtimeMs": 51552,
      "success": true
    },
    {
      "month": "2023-11",
      "startDate": "2023-11-01",
      "endDate": "2023-11-30",
      "trades": 35,
      "winRate": 22.857142857142858,
      "totalPnL": -1600.8120001932552,
      "profitFactor": 0.8706955742878705,
      "avgRR": 1.4571428571428575,
      "maxDrawdown": 1976.6767723514622,
      "maxDrawdownPercent": 19.766767723514622,
      "totalReturn": -1600.8120001932548,
      "totalReturnPercent": -16.00812000193255,
      "expectancy": -45.737485719807296,
      "runtimeMs": 51257,
      "success": true
    },
    {
      "month": "2023-12",
      "startDate": "2023-12-01",
      "endDate": "2023-12-31",
      "trades": 50,
      "winRate": 18,
      "totalPnL": -5393.14073807674,
      "profitFactor": 0.7052891227818361,
      "avgRR": 1.3599999999999988,
      "maxDrawdown": 6329.381037874215,
      "maxDrawdownPercent": 57.651107341726245,
      "totalReturn": -5393.14073807674,
      "totalReturnPercent": -53.931407380767396,
      "expectancy": -107.86281476153476,
      "runtimeMs": 49806,
      "success": true
    }
  ],
  "summary": {
    "totalMonths": 12,
    "profitableMonths": 2,
    "losingMonths": 10,
    "totalTrades": 499,
    "avgTradesPerMonth": 41.583333333333336,
    "avgWinRate": 21.5170576238275,
    "totalPnL": -30247.047525778973,
    "avgMonthlyReturn": -25.20587293814913,
    "avgProfitFactor": 0.8120430188898142,
    "avgRR": 1.4303411524765501,
    "maxDrawdown": 6329.381037874215,
    "maxDrawdownPercent": 61.36719448537063,
    "bestMonth": {
      "month": "2023-06",
      "startDate": "2023-06-01",
      "endDate": "2023-06-30",
      "trades": 41,
      "winRate": 26.82926829268293,
      "totalPnL": 1028.1886338186382,
      "profitFactor": 1.0677410717790232,
      "avgRR": 1.5365853658536592,
      "maxDrawdown": 2258.50224802487,
      "maxDrawdownPercent": 21.431468323292936,
      "totalReturn": 1028.1886338186432,
      "totalReturnPercent": 10.281886338186432,
      "expectancy": 25.077771556552136,
      "runtimeMs": 44605,
      "success": true
    },
    "worstMonth": {
      "month": "2023-01",
      "startDate": "2023-01-01",
      "endDate": "2023-01-31",
      "trades": 55,
      "winRate": 16.363636363636363,
      "totalPnL": -5932.5425893233105,
      "profitFactor": 0.5860197861055068,
      "avgRR": 1.327272727272727,
      "maxDrawdown": 6136.719448537064,
      "maxDrawdownPercent": 61.36719448537063,
      "totalReturn": -5932.542589323311,
      "totalReturnPercent": -59.32542589323312,
      "expectancy": -107.86441071496938,
      "runtimeMs": 63502,
      "success": true
    },
    "profitableMonthsList": [
      "2023-06",
      "2023-07"
    ],
    "losingMonthsList": [
      "2023-01",
      "2023-02",
      "2023-03",
      "2023-04",
      "2023-05",
      "2023-08",
      "2023-09",
      "2023-10",
      "2023-11",
      "2023-12"
    ]
  }
}